clippy/__init__.py
clippy/__main__.py
clippy/__version__.py
clippy/diff_utils.py
clippy/executor.py
clippy/file_validators.py
clippy/models.py
clippy/models.yaml
clippy/permissions.py
clippy/prompts.py
clippy/providers.py
clippy/settings.py
clippy/utils.py
clippy/agent/__init__.py
clippy/agent/auto_mode.py
clippy/agent/command_safety_checker.py
clippy/agent/conversation.py
clippy/agent/core.py
clippy/agent/errors.py
clippy/agent/exceptions.py
clippy/agent/loop.py
clippy/agent/mcp_manager.py
clippy/agent/protocols.py
clippy/agent/subagent.py
clippy/agent/subagent_cache.py
clippy/agent/subagent_chainer.py
clippy/agent/subagent_config_manager.py
clippy/agent/subagent_manager.py
clippy/agent/subagent_monitor.py
clippy/agent/subagent_types.py
clippy/agent/subagent_utils.py
clippy/agent/token_tracker.py
clippy/agent/tool_handler.py
clippy/agent/utils.py
clippy/cli/__init__.py
clippy/cli/auth_cli.py
clippy/cli/commands_main.py
clippy/cli/completion.py
clippy/cli/custom_cli.py
clippy/cli/custom_cli_wizards.py
clippy/cli/custom_commands.py
clippy/cli/first_time_setup.py
clippy/cli/main.py
clippy/cli/oneshot.py
clippy/cli/parser.py
clippy/cli/repl.py
clippy/cli/setup.py
clippy/cli/commands/__init__.py
clippy/cli/commands/auto.py
clippy/cli/commands/init.py
clippy/cli/commands/mcp.py
clippy/cli/commands/model.py
clippy/cli/commands/provider.py
clippy/cli/commands/safety.py
clippy/cli/commands/session.py
clippy/cli/commands/subagent.py
clippy/cli/commands/system.py
clippy/llm/__init__.py
clippy/llm/anthropic.py
clippy/llm/base.py
clippy/llm/errors.py
clippy/llm/google.py
clippy/llm/http_client.py
clippy/llm/openai.py
clippy/llm/utils.py
clippy/mcp/__init__.py
clippy/mcp/config.py
clippy/mcp/errors.py
clippy/mcp/manager.py
clippy/mcp/naming.py
clippy/mcp/schema.py
clippy/mcp/transports.py
clippy/mcp/trust.py
clippy/mcp/types.py
clippy/oauth/__init__.py
clippy/oauth/claude_code.py
clippy/tools/__init__.py
clippy/tools/catalog.py
clippy/tools/copy_file.py
clippy_code-4.21.0.dist-info/METADATA
clippy_code-4.21.0.dist-info/WHEEL
clippy_code-4.21.0.dist-info/entry_points.txt
clippy_code-4.21.0.dist-info/licenses/LICENSE
clippy_code-4.21.0.dist-info/RECORD
