Metadata-Version: 2.4
Name: clippy-code
Version: 4.21.0
Summary: A powerful CLI coding agent powered by OpenAI-compatible LLMs
Project-URL: Homepage, https://github.com/cellwebb/clippy-code
Project-URL: Repository, https://github.com/cellwebb/clippy-code
Project-URL: Issues, https://github.com/cellwebb/clippy-code/issues
Project-URL: Documentation, https://github.com/cellwebb/clippy-code#readme
Author-email: Cell Webb <cellwebb@users.noreply.github.com>
License: MIT
License-File: LICENSE
Keywords: ai,cerebras,cli,coding-agent,developer-tools,llm,ollama,openai
Classifier: Development Status :: 4 - Beta
Classifier: Environment :: Console
Classifier: Intended Audience :: Developers
Classifier: License :: OSI Approved :: MIT License
Classifier: Operating System :: OS Independent
Classifier: Programming Language :: Python :: 3
Classifier: Programming Language :: Python :: 3.10
Classifier: Programming Language :: Python :: 3.11
Classifier: Programming Language :: Python :: 3.12
Classifier: Programming Language :: Python :: 3.13
Classifier: Topic :: Software Development
Classifier: Topic :: Software Development :: Code Generators
Classifier: Topic :: Utilities
Requires-Python: >=3.10
Requires-Dist: httpx>=0.28.0
Requires-Dist: mcp>=1.18.0
Requires-Dist: pathspec>=0.12.1
Requires-Dist: prompt-toolkit>=3.0.52
Requires-Dist: pydantic>=2.12.3
Requires-Dist: python-dotenv>=1.1.1
Requires-Dist: pyyaml>=6.0.3
Requires-Dist: questionary>=2.0.1
Requires-Dist: rapidfuzz>=3.0.0
Requires-Dist: requests>=2.31.0
Requires-Dist: rich>=14.2.0
Requires-Dist: tenacity>=9.1.2
Requires-Dist: tiktoken>=0.12.0
Provides-Extra: dev
Requires-Dist: mypy>=1.18.2; extra == 'dev'
Requires-Dist: pytest-asyncio>=0.25.2; extra == 'dev'
Requires-Dist: pytest-cov>=7.0.0; extra == 'dev'
Requires-Dist: pytest>=8.4.2; extra == 'dev'
Requires-Dist: ruff>=0.14.1; extra == 'dev'
Requires-Dist: types-pyyaml>=6.0.12.20250915; extra == 'dev'
Requires-Dist: types-requests>=2.32.0; extra == 'dev'
